fbracrypto/__init__.py
fbracrypto/crypto.py
fbra_crypto-0.0.1.dist-info/LICENSE
fbra_crypto-0.0.1.dist-info/METADATA
fbra_crypto-0.0.1.dist-info/WHEEL
fbra_crypto-0.0.1.dist-info/top_level.txt
fbra_crypto-0.0.1.dist-info/RECORD
