Metadata-Version: 2.1
Name: fbra-crypto
Version: 0.0.1
Summary: cipher and decipher values
Author: Felix Brändli
Author-email: 
Keywords: python
Classifier: Programming Language :: Python :: 3
Classifier: License :: OSI Approved :: GNU General Public License v3 (GPLv3)
Classifier: Operating System :: OS Independent
Requires-Python: >=3.10
License-File: LICENSE
Requires-Dist: cryptography
